{
  "ComponentIndexes": {},
  "ControlUniqueIds": {
    "App": 1,
    "Button1": 5,
    "Screen1": 3,
    "Screen2": 4
  },
  "FunctionParamsInvariantScripts": {},
  "HeaderLastSavedDateTimeUTC": "01/31/2022 09:58:49",
  "LocalDatabaseReferencesAsEmpty": false,
  "LocalResourceFileNames": {},
  "LocalResourceRootPaths": {},
  "OrderComponentMetadata": {},
  "OrderComponentTemplate": {},
  "OrderDataSource": {},
  "OrderGroupControls": {},
  "OrderTemplate": {},
  "OrderXMLTemplate": {
    "button": 0
  },
  "PublishOrderIndices": {
    "App": 0,
    "Button1": 0,
    "Screen1": 0,
    "Screen2": 0
  },
  "ResourcesJsonIndices": {},
  "TemplateVersions": {},
  "VolatileProperties": {
    "AnalysisLoadTime": 0.0429599,
    "ControlCount": {
      "screen": 1
    },
    "DeserializationLoadTime": 0.4957732,
    "ErrorCount": 0
  }
}